confar/__init__.py
confar/aggregate.py
confar/cli.py
confar/runner.py
confar/utils/__init__.py
confar/utils/Emitter/__init__.py
confar/utils/map/__init__.py
confar/utils/parser/__init__.py
confar/utils/parser/json.py
confar/utils/parser/yaml.py
confar/utils/task/__init__.py
confar/utils/task/shell.py
confar-1.1.5.dist-info/LICENSE
confar-1.1.5.dist-info/METADATA
confar-1.1.5.dist-info/WHEEL
confar-1.1.5.dist-info/entry_points.txt
confar-1.1.5.dist-info/top_level.txt
confar-1.1.5.dist-info/RECORD
