Metadata-Version: 2.1
Name: confar
Version: 1.1.5
Summary: Confar is a Python CLI and library for configuration management, designed to aggregate and manage configuration data and execute tasks based on that configuration.
Home-page: https://github.com/sanjairocky/confar
Author: sanjai Rocky
Author-email: talk2sanjai@gmail.com
Project-URL: Bug Tracker, https://github.com/sanjairocky/confar/issues
Project-URL: repository, https://github.com/sanjairocky/confar
Classifier: Programming Language :: Python :: 3
Classifier: License :: OSI Approved :: MIT License
Classifier: Operating System :: OS Independent
Requires-Python: >=3.9
License-File: LICENSE
Requires-Dist: PyYAML
Requires-Dist: typer[all]
